FTCircuitSynthesizer/DirectedAcyclicGraph.py
FTCircuitSynthesizer/DistanceMatrix.py
FTCircuitSynthesizer/SABRE_FTQC_public_single.py
FTCircuitSynthesizer/SABRE_utility.py
FTCircuitSynthesizer/__init__.py
FTCircuitSynthesizer/checkup.py
FTCircuitSynthesizer/depth_analysis.py
FTCircuitSynthesizer/error.py
FTCircuitSynthesizer/formatconversion.py
FTCircuitSynthesizer/globalVariable.py
FTCircuitSynthesizer/postprocess.py
FTCircuitSynthesizer/util.py
tests/__init__.py
tests/layout_generator.py
tests/test.py
tests/util.py
ftcircuitsynthesis-0.0.1.dist-info/METADATA
ftcircuitsynthesis-0.0.1.dist-info/NOTICE.md
ftcircuitsynthesis-0.0.1.dist-info/WHEEL
ftcircuitsynthesis-0.0.1.dist-info/top_level.txt
ftcircuitsynthesis-0.0.1.dist-info/RECORD
