Metadata-Version: 2.1
Name: ftcircuitsynthesis
Version: 0.0.1
Summary: fault tolerant circuit synthesis for universal fault-tolerant quantum computing based on concatenated codes
Home-page: UNKNOWN
Author: Yongsoo Hwang
Author-email: yhwang@etri.re.kr
License: UNKNOWN
Platform: UNKNOWN
Requires-Python: >=3
License-File: NOTICE.md
Requires-Dist: simplejson
Requires-Dist: icecream
Requires-Dist: qubitmapping
Requires-Dist: userproperty
